agenthub/__init__.py
agenthub/attp/__init__.py
agenthub/attp/attp_tool.py
agenthub/attp/context.py
agenthub/attp/pipe.py
agenthub/attp/standalone_tool.py
agenthub/attp/tool_marker.py
agenthub/cli/__init__.py
agenthub/cli/agents.py
agenthub/cli/copilot.py
agenthub/configs/__init__.py
agenthub/configs/main.py
agenthub/copilot/__init__.py
agenthub/copilot/sdk.py
agenthub/copilot/templates/agent_creation_copilot.prompt
agenthub/copilot/tools.py
agenthub/copilot/ui.py
agenthub/core/__init__.py
agenthub/core/scaffolds/__init__.py
agenthub/core/scaffolds/engine.py
agenthub/interfaces/__init__.py
agenthub/interfaces/scaffold_module.py
agenthub/interfaces/scaffolds/__init__.py
agenthub/interfaces/scaffolds/autonomous_agent.py
agenthub/interfaces/scaffolds/common_agent.py
agenthub/interfaces/scaffolds/router_agent.py
agenthub/interfaces/types/__init__.py
agenthub/interfaces/types/tool_metadata.py
agenthub/mcp/__init__.py
agenthub/mcp/controller_hook.py
agenthub/mcp/server.py
agenthub/providers/__init__.py
agenthub/providers/agenthub_provider.py
agenthub/scaffolds/__init__.py
agenthub/scaffolds/autonomous_agent.py
agenthub/scaffolds/common_agent.py
agenthub/scaffolds/router_agent.py
scaffolds/__init__.py
scaffolds/agent_creation_copilot.prompt
scaffolds/agent_creation_copilot.py
scaffolds/test_common_agent.prompt
scaffolds/test_common_agent.py
agent_scaffolds-0.1.7.dist-info/LICENSE
agent_scaffolds-0.1.7.dist-info/METADATA
agent_scaffolds-0.1.7.dist-info/WHEEL
agent_scaffolds-0.1.7.dist-info/RECORD
