Metadata-Version: 2.3
Name: agent-scaffolds
Version: 0.1.7
Summary: agent-scaffolds
Author: Zahcoder34
Author-email: Zakhriw@gmail.com
Requires-Python: >=3.11,<3.14
Classifier: Programming Language :: Python :: 3
Classifier: Programming Language :: Python :: 3.11
Classifier: Programming Language :: Python :: 3.12
Classifier: Programming Language :: Python :: 3.13
Requires-Dist: ascender-framework (>=2.0.4,<3.0.0)
Requires-Dist: attp-client (==0.0.19b6)
Requires-Dist: prompt-toolkit (>=3.0.45,<4.0.0)
